mklearn/__init__.py
mklearn/dt.py
mklearn/knn.py
mklearn/mlr.py
mklearn-0.0.5.dist-info/LICENSE
mklearn-0.0.5.dist-info/METADATA
mklearn-0.0.5.dist-info/WHEEL
mklearn-0.0.5.dist-info/top_level.txt
mklearn-0.0.5.dist-info/RECORD
