Metadata-Version: 2.1
Name: mklearn
Version: 0.0.5
Summary: mlkit-learn: lightweight machine learning algorithms for learning.
Home-page: https://github.com/ryanxjhan/mlkit-learn
Author: Ryan Han
Author-email: ryan.han@uwaterloo.ca
License: UNKNOWN
Platform: UNKNOWN
Classifier: Programming Language :: Python :: 3
Classifier: License :: OSI Approved :: MIT License
Classifier: Operating System :: OS Independent
Requires-Dist: numpy
Requires-Dist: pandas
Requires-Dist: sklearn
